{"nodes": [{"id": "c_users_harsh_onedrive_desktop_mini_project_campustrade_app_core_auth_dependency_py", "label": "auth_dependency.py", "file_type": "code", "source_file": "C:\\Users\\harsh\\OneDrive\\Desktop\\MINI Project\\CampusTrade\\app\\core\\auth_dependency.py", "source_location": "L1"}, {"id": "auth_dependency_get_current_user_id", "label": "get_current_user_id()", "file_type": "code", "source_file": "C:\\Users\\harsh\\OneDrive\\Desktop\\MINI Project\\CampusTrade\\app\\core\\auth_dependency.py", "source_location": "L21"}, {"id": "auth_dependency_rationale_1", "label": "Auth dependency \u2014 verifies the Supabase JWT and returns the current user ID.  Us", "file_type": "rationale", "source_file": "C:\\Users\\harsh\\OneDrive\\Desktop\\MINI Project\\CampusTrade\\app\\core\\auth_dependency.py", "source_location": "L1"}, {"id": "auth_dependency_rationale_24", "label": "Validate the Bearer token via Supabase ``auth.get_user()``.      Returns:", "file_type": "rationale", "source_file": "C:\\Users\\harsh\\OneDrive\\Desktop\\MINI Project\\CampusTrade\\app\\core\\auth_dependency.py", "source_location": "L24"}], "edges": [{"source": "c_users_harsh_onedrive_desktop_mini_project_campustrade_app_core_auth_dependency_py", "target": "fastapi", "relation": "imports_from", "confidence": "EXTRACTED", "source_file": "C:\\Users\\harsh\\OneDrive\\Desktop\\MINI Project\\CampusTrade\\app\\core\\auth_dependency.py", "source_location": "L12", "weight": 1.0}, {"source": "c_users_harsh_onedrive_desktop_mini_project_campustrade_app_core_auth_dependency_py", "target": "fastapi_security", "relation": "imports_from", "confidence": "EXTRACTED", "source_file": "C:\\Users\\harsh\\OneDrive\\Desktop\\MINI Project\\CampusTrade\\app\\core\\auth_dependency.py", "source_location": "L13", "weight": 1.0}, {"source": "c_users_harsh_onedrive_desktop_mini_project_campustrade_app_core_auth_dependency_py", "target": "app_core_supabase_client", "relation": "imports_from", "confidence": "EXTRACTED", "source_file": "C:\\Users\\harsh\\OneDrive\\Desktop\\MINI Project\\CampusTrade\\app\\core\\auth_dependency.py", "source_location": "L15", "weight": 1.0}, {"source": "c_users_harsh_onedrive_desktop_mini_project_campustrade_app_core_auth_dependency_py", "target": "auth_dependency_get_current_user_id", "relation": "contains", "confidence": "EXTRACTED", "source_file": "C:\\Users\\harsh\\OneDrive\\Desktop\\MINI Project\\CampusTrade\\app\\core\\auth_dependency.py", "source_location": "L21", "weight": 1.0}, {"source": "auth_dependency_rationale_1", "target": "c_users_harsh_onedrive_desktop_mini_project_campustrade_app_core_auth_dependency_py", "relation": "rationale_for", "confidence": "EXTRACTED", "source_file": "C:\\Users\\harsh\\OneDrive\\Desktop\\MINI Project\\CampusTrade\\app\\core\\auth_dependency.py", "source_location": "L1", "weight": 1.0}, {"source": "auth_dependency_rationale_24", "target": "auth_dependency_get_current_user_id", "relation": "rationale_for", "confidence": "EXTRACTED", "source_file": "C:\\Users\\harsh\\OneDrive\\Desktop\\MINI Project\\CampusTrade\\app\\core\\auth_dependency.py", "source_location": "L24", "weight": 1.0}], "raw_calls": [{"caller_nid": "auth_dependency_get_current_user_id", "callee": "get_supabase_client", "source_file": "C:\\Users\\harsh\\OneDrive\\Desktop\\MINI Project\\CampusTrade\\app\\core\\auth_dependency.py", "source_location": "L34"}, {"caller_nid": "auth_dependency_get_current_user_id", "callee": "get_user", "source_file": "C:\\Users\\harsh\\OneDrive\\Desktop\\MINI Project\\CampusTrade\\app\\core\\auth_dependency.py", "source_location": "L37"}, {"caller_nid": "auth_dependency_get_current_user_id", "callee": "HTTPException", "source_file": "C:\\Users\\harsh\\OneDrive\\Desktop\\MINI Project\\CampusTrade\\app\\core\\auth_dependency.py", "source_location": "L39"}, {"caller_nid": "auth_dependency_get_current_user_id", "callee": "HTTPException", "source_file": "C:\\Users\\harsh\\OneDrive\\Desktop\\MINI Project\\CampusTrade\\app\\core\\auth_dependency.py", "source_location": "L46"}, {"caller_nid": "auth_dependency_get_current_user_id", "callee": "str", "source_file": "C:\\Users\\harsh\\OneDrive\\Desktop\\MINI Project\\CampusTrade\\app\\core\\auth_dependency.py", "source_location": "L52"}]}